Metadata-Version: 2.1
Name: pystonkslib
Version: 0.0.4
Summary: This is a stonks data pulling library
Home-page: https://gitlab.com/bubthegreat/pystonkslib
Author: Micheal Taylor
Author-email: bubthegreat@gmail.com
License: UNKNOWN
Platform: UNKNOWN
Requires-Python: >=3.6.6
